README
setup.py
qmonitor_client/__init__.py
qmonitor_client/core.py
qmonitor_client/decorator.py
qmonitor_client/exposition.py
qmonitor_client/multiprocess.py
qmonitor_client/parser.py
qmonitor_client/platform_collector.py
qmonitor_client/process_collector.py
qmonitor_client/task.py
qmonitor_client.egg-info/PKG-INFO
qmonitor_client.egg-info/SOURCES.txt
qmonitor_client.egg-info/dependency_links.txt
qmonitor_client.egg-info/requires.txt
qmonitor_client.egg-info/top_level.txt
qmonitor_client/bridge/__init__.py
qmonitor_client/bridge/graphite.py
qmonitor_client/twisted/__init__.py
qmonitor_client/twisted/_exposition.py