Metadata-Version: 1.0
Name: qmonitor-client
Version: 0.1.0
Summary: Python client for qmonitor, based on Prometheus Python Client
Home-page: https://github.com/shadow4125/py_qmonitor
Author: shadow.zhang
Author-email: shadowyue4125@gmail.com
License: UNKNOWN
Platform: UNKNOWN
